{
  "aggregate": {
    "counters": {
      "vusers.created_by_name.Create discussions with text only": 223,
      "vusers.created": 270,
      "http.requests": 669,
      "http.codes.201": 669,
      "http.responses": 669,
      "http.downloaded_bytes": 565927,
      "plugins.metrics-by-endpoint./api/v1/discussions.codes.201": 669,
      "plugins.expect.ok": 669,
      "plugins.expect.ok.statusCode": 669,
      "vusers.failed": 0,
      "vusers.completed": 270,
      "vusers.created_by_name.Create discussions with file attachments": 47,
      "requests.total": 94,
      "responses.201": 94,
      "requests.succeeded": 94
    },
    "rates": {
      "http.request_rate": 13
    },
    "firstCounterAt": 1743341416084,
    "firstHistogramAt": 1743341416238,
    "lastCounterAt": 1743341479776,
    "lastHistogramAt": 1743341479776,
    "firstMetricAt": 1743341416084,
    "lastMetricAt": 1743341479776,
    "period": 1743341470000,
    "summaries": {
      "http.response_time": {
        "min": 5,
        "max": 53,
        "count": 669,
        "mean": 7.7,
        "p50": 7,
        "median": 7,
        "p75": 7.9,
        "p90": 10.1,
        "p95": 15,
        "p99": 16.9,
        "p999": 47.9
      },
      "http.response_time.2xx": {
        "min": 5,
        "max": 53,
        "count": 669,
        "mean": 7.7,
        "p50": 7,
        "median": 7,
        "p75": 7.9,
        "p90": 10.1,
        "p95": 15,
        "p99": 16.9,
        "p999": 47.9
      },
      "plugins.metrics-by-endpoint.response_time./api/v1/discussions": {
        "min": 5,
        "max": 53,
        "count": 669,
        "mean": 7.7,
        "p50": 7,
        "median": 7,
        "p75": 7.9,
        "p90": 10.1,
        "p95": 15,
        "p99": 16.9,
        "p999": 47.9
      },
      "vusers.session_length": {
        "min": 22.8,
        "max": 4132.6,
        "count": 270,
        "mean": 773,
        "p50": 89.1,
        "median": 89.1,
        "p75": 100.5,
        "p90": 4065.2,
        "p95": 4147.4,
        "p99": 4147.4,
        "p999": 4147.4
      }
    },
    "histograms": {
      "http.response_time": {
        "min": 5,
        "max": 53,
        "count": 669,
        "mean": 7.7,
        "p50": 7,
        "median": 7,
        "p75": 7.9,
        "p90": 10.1,
        "p95": 15,
        "p99": 16.9,
        "p999": 47.9
      },
      "http.response_time.2xx": {
        "min": 5,
        "max": 53,
        "count": 669,
        "mean": 7.7,
        "p50": 7,
        "median": 7,
        "p75": 7.9,
        "p90": 10.1,
        "p95": 15,
        "p99": 16.9,
        "p999": 47.9
      },
      "plugins.metrics-by-endpoint.response_time./api/v1/discussions": {
        "min": 5,
        "max": 53,
        "count": 669,
        "mean": 7.7,
        "p50": 7,
        "median": 7,
        "p75": 7.9,
        "p90": 10.1,
        "p95": 15,
        "p99": 16.9,
        "p999": 47.9
      },
      "vusers.session_length": {
        "min": 22.8,
        "max": 4132.6,
        "count": 270,
        "mean": 773,
        "p50": 89.1,
        "median": 89.1,
        "p75": 100.5,
        "p90": 4065.2,
        "p95": 4147.4,
        "p99": 4147.4,
        "p999": 4147.4
      }
    }
  },
  "intermediate": [
    {
      "counters": {
        "vusers.created_by_name.Create discussions with text only": 4,
        "vusers.created": 4,
        "http.requests": 12,
        "http.codes.201": 12,
        "http.responses": 12,
        "http.downloaded_bytes": 10353,
        "plugins.metrics-by-endpoint./api/v1/discussions.codes.201": 12,
        "plugins.expect.ok": 12,
        "plugins.expect.ok.statusCode": 12,
        "vusers.failed": 0,
        "vusers.completed": 4
      },
      "rates": {
        "http.request_rate": 4
      },
      "http.request_rate": null,
      "firstCounterAt": 1743341416084,
      "firstHistogramAt": 1743341416238,
      "lastCounterAt": 1743341419197,
      "lastHistogramAt": 1743341419197,
      "firstMetricAt": 1743341416084,
      "lastMetricAt": 1743341419197,
      "period": "1743341410000",
      "summaries": {
        "http.response_time": {
          "min": 6,
          "max": 53,
          "count": 12,
          "mean": 12.4,
          "p50": 6,
          "median": 6,
          "p75": 15,
          "p90": 15,
          "p95": 16.9,
          "p99": 16.9,
          "p999": 16.9
        },
        "http.response_time.2xx": {
          "min": 6,
          "max": 53,
          "count": 12,
          "mean": 12.4,
          "p50": 6,
          "median": 6,
          "p75": 15,
          "p90": 15,
          "p95": 16.9,
          "p99": 16.9,
          "p999": 16.9
        },
        "plugins.metrics-by-endpoint.response_time./api/v1/discussions": {
          "min": 6,
          "max": 53,
          "count": 12,
          "mean": 12.4,
          "p50": 6,
          "median": 6,
          "p75": 15,
          "p90": 15,
          "p95": 16.9,
          "p99": 16.9,
          "p999": 16.9
        },
        "vusers.session_length": {
          "min": 98.7,
          "max": 176.6,
          "count": 4,
          "mean": 119.8,
          "p50": 102.5,
          "median": 102.5,
          "p75": 102.5,
          "p90": 102.5,
          "p95": 102.5,
          "p99": 102.5,
          "p999": 102.5
        }
      },
      "histograms": {
        "http.response_time": {
          "min": 6,
          "max": 53,
          "count": 12,
          "mean": 12.4,
          "p50": 6,
          "median": 6,
          "p75": 15,
          "p90": 15,
          "p95": 16.9,
          "p99": 16.9,
          "p999": 16.9
        },
        "http.response_time.2xx": {
          "min": 6,
          "max": 53,
          "count": 12,
          "mean": 12.4,
          "p50": 6,
          "median": 6,
          "p75": 15,
          "p90": 15,
          "p95": 16.9,
          "p99": 16.9,
          "p999": 16.9
        },
        "plugins.metrics-by-endpoint.response_time./api/v1/discussions": {
          "min": 6,
          "max": 53,
          "count": 12,
          "mean": 12.4,
          "p50": 6,
          "median": 6,
          "p75": 15,
          "p90": 15,
          "p95": 16.9,
          "p99": 16.9,
          "p999": 16.9
        },
        "vusers.session_length": {
          "min": 98.7,
          "max": 176.6,
          "count": 4,
          "mean": 119.8,
          "p50": 102.5,
          "median": 102.5,
          "p75": 102.5,
          "p90": 102.5,
          "p95": 102.5,
          "p99": 102.5,
          "p999": 102.5
        }
      }
    },
    {
      "counters": {
        "vusers.created_by_name.Create discussions with text only": 14,
        "vusers.created": 20,
        "http.requests": 42,
        "http.codes.201": 42,
        "http.responses": 42,
        "http.downloaded_bytes": 34327,
        "plugins.metrics-by-endpoint./api/v1/discussions.codes.201": 42,
        "plugins.expect.ok": 42,
        "plugins.expect.ok.statusCode": 42,
        "vusers.failed": 0,
        "vusers.completed": 18,
        "vusers.created_by_name.Create discussions with file attachments": 6,
        "requests.total": 11,
        "responses.201": 11,
        "requests.succeeded": 11
      },
      "rates": {
        "http.request_rate": 8
      },
      "http.request_rate": null,
      "firstCounterAt": 1743341420112,
      "firstHistogramAt": 1743341420197,
      "lastCounterAt": 1743341429445,
      "lastHistogramAt": 1743341429445,
      "firstMetricAt": 1743341420112,
      "lastMetricAt": 1743341429445,
      "period": "1743341420000",
      "summaries": {
        "http.response_time": {
          "min": 5,
          "max": 17,
          "count": 42,
          "mean": 7.9,
          "p50": 7,
          "median": 7,
          "p75": 7.9,
          "p90": 10.1,
          "p95": 15,
          "p99": 16.9,
          "p999": 16.9
        },
        "http.response_time.2xx": {
          "min": 5,
          "max": 17,
          "count": 42,
          "mean": 7.9,
          "p50": 7,
          "median": 7,
          "p75": 7.9,
          "p90": 10.1,
          "p95": 15,
          "p99": 16.9,
          "p999": 16.9
        },
        "plugins.metrics-by-endpoint.response_time./api/v1/discussions": {
          "min": 5,
          "max": 17,
          "count": 42,
          "mean": 7.9,
          "p50": 7,
          "median": 7,
          "p75": 7.9,
          "p90": 10.1,
          "p95": 15,
          "p99": 16.9,
          "p999": 16.9
        },
        "vusers.session_length": {
          "min": 35,
          "max": 4102.9,
          "count": 18,
          "mean": 978.9,
          "p50": 98.5,
          "median": 98.5,
          "p75": 125.2,
          "p90": 4065.2,
          "p95": 4065.2,
          "p99": 4065.2,
          "p999": 4065.2
        }
      },
      "histograms": {
        "http.response_time": {
          "min": 5,
          "max": 17,
          "count": 42,
          "mean": 7.9,
          "p50": 7,
          "median": 7,
          "p75": 7.9,
          "p90": 10.1,
          "p95": 15,
          "p99": 16.9,
          "p999": 16.9
        },
        "http.response_time.2xx": {
          "min": 5,
          "max": 17,
          "count": 42,
          "mean": 7.9,
          "p50": 7,
          "median": 7,
          "p75": 7.9,
          "p90": 10.1,
          "p95": 15,
          "p99": 16.9,
          "p999": 16.9
        },
        "plugins.metrics-by-endpoint.response_time./api/v1/discussions": {
          "min": 5,
          "max": 17,
          "count": 42,
          "mean": 7.9,
          "p50": 7,
          "median": 7,
          "p75": 7.9,
          "p90": 10.1,
          "p95": 15,
          "p99": 16.9,
          "p999": 16.9
        },
        "vusers.session_length": {
          "min": 35,
          "max": 4102.9,
          "count": 18,
          "mean": 978.9,
          "p50": 98.5,
          "median": 98.5,
          "p75": 125.2,
          "p90": 4065.2,
          "p95": 4065.2,
          "p99": 4065.2,
          "p999": 4065.2
        }
      }
    },
    {
      "counters": {
        "vusers.created_by_name.Create discussions with text only": 26,
        "vusers.created": 32,
        "http.requests": 78,
        "http.codes.201": 78,
        "http.responses": 78,
        "http.downloaded_bytes": 66660,
        "plugins.metrics-by-endpoint./api/v1/discussions.codes.201": 78,
        "plugins.expect.ok": 78,
        "plugins.expect.ok.statusCode": 78,
        "vusers.failed": 0,
        "vusers.completed": 31,
        "requests.total": 11,
        "responses.201": 11,
        "requests.succeeded": 11,
        "vusers.created_by_name.Create discussions with file attachments": 6
      },
      "rates": {
        "http.request_rate": 11
      },
      "http.request_rate": null,
      "firstCounterAt": 1743341430163,
      "firstHistogramAt": 1743341430247,
      "lastCounterAt": 1743341439528,
      "lastHistogramAt": 1743341439460,
      "firstMetricAt": 1743341430163,
      "lastMetricAt": 1743341439528,
      "period": "1743341430000",
      "summaries": {
        "http.response_time": {
          "min": 5,
          "max": 18,
          "count": 78,
          "mean": 7.5,
          "p50": 6,
          "median": 6,
          "p75": 7,
          "p90": 10.1,
          "p95": 16,
          "p99": 16.9,
          "p999": 16.9
        },
        "http.response_time.2xx": {
          "min": 5,
          "max": 18,
          "count": 78,
          "mean": 7.5,
          "p50": 6,
          "median": 6,
          "p75": 7,
          "p90": 10.1,
          "p95": 16,
          "p99": 16.9,
          "p999": 16.9
        },
        "plugins.metrics-by-endpoint.response_time./api/v1/discussions": {
          "min": 5,
          "max": 18,
          "count": 78,
          "mean": 7.5,
          "p50": 6,
          "median": 6,
          "p75": 7,
          "p90": 10.1,
          "p95": 16,
          "p99": 16.9,
          "p999": 16.9
        },
        "vusers.session_length": {
          "min": 24.1,
          "max": 4116,
          "count": 31,
          "mean": 729.3,
          "p50": 90.9,
          "median": 90.9,
          "p75": 96.6,
          "p90": 4065.2,
          "p95": 4065.2,
          "p99": 4147.4,
          "p999": 4147.4
        }
      },
      "histograms": {
        "http.response_time": {
          "min": 5,
          "max": 18,
          "count": 78,
          "mean": 7.5,
          "p50": 6,
          "median": 6,
          "p75": 7,
          "p90": 10.1,
          "p95": 16,
          "p99": 16.9,
          "p999": 16.9
        },
        "http.response_time.2xx": {
          "min": 5,
          "max": 18,
          "count": 78,
          "mean": 7.5,
          "p50": 6,
          "median": 6,
          "p75": 7,
          "p90": 10.1,
          "p95": 16,
          "p99": 16.9,
          "p999": 16.9
        },
        "plugins.metrics-by-endpoint.response_time./api/v1/discussions": {
          "min": 5,
          "max": 18,
          "count": 78,
          "mean": 7.5,
          "p50": 6,
          "median": 6,
          "p75": 7,
          "p90": 10.1,
          "p95": 16,
          "p99": 16.9,
          "p999": 16.9
        },
        "vusers.session_length": {
          "min": 24.1,
          "max": 4116,
          "count": 31,
          "mean": 729.3,
          "p50": 90.9,
          "median": 90.9,
          "p75": 96.6,
          "p90": 4065.2,
          "p95": 4065.2,
          "p99": 4147.4,
          "p999": 4147.4
        }
      }
    },
    {
      "counters": {
        "vusers.created_by_name.Create discussions with text only": 39,
        "vusers.created": 44,
        "http.requests": 117,
        "http.codes.201": 117,
        "http.responses": 117,
        "http.downloaded_bytes": 99302,
        "plugins.metrics-by-endpoint./api/v1/discussions.codes.201": 117,
        "plugins.expect.ok": 117,
        "plugins.expect.ok.statusCode": 117,
        "vusers.failed": 0,
        "vusers.completed": 44,
        "vusers.created_by_name.Create discussions with file attachments": 5,
        "requests.total": 11,
        "responses.201": 11,
        "requests.succeeded": 11
      },
      "rates": {
        "http.request_rate": 16
      },
      "http.request_rate": null,
      "firstCounterAt": 1743341440222,
      "firstHistogramAt": 1743341440303,
      "lastCounterAt": 1743341449672,
      "lastHistogramAt": 1743341449672,
      "firstMetricAt": 1743341440222,
      "lastMetricAt": 1743341449672,
      "period": "1743341440000",
      "summaries": {
        "http.response_time": {
          "min": 5,
          "max": 47,
          "count": 117,
          "mean": 7.5,
          "p50": 6,
          "median": 6,
          "p75": 7,
          "p90": 8.9,
          "p95": 13.9,
          "p99": 16,
          "p999": 18
        },
        "http.response_time.2xx": {
          "min": 5,
          "max": 47,
          "count": 117,
          "mean": 7.5,
          "p50": 6,
          "median": 6,
          "p75": 7,
          "p90": 8.9,
          "p95": 13.9,
          "p99": 16,
          "p999": 18
        },
        "plugins.metrics-by-endpoint.response_time./api/v1/discussions": {
          "min": 5,
          "max": 47,
          "count": 117,
          "mean": 7.5,
          "p50": 6,
          "median": 6,
          "p75": 7,
          "p90": 8.9,
          "p95": 13.9,
          "p99": 16,
          "p999": 18
        },
        "vusers.session_length": {
          "min": 24,
          "max": 4123.8,
          "count": 44,
          "mean": 536.6,
          "p50": 89.1,
          "median": 89.1,
          "p75": 98.5,
          "p90": 135.7,
          "p95": 4065.2,
          "p99": 4147.4,
          "p999": 4147.4
        }
      },
      "histograms": {
        "http.response_time": {
          "min": 5,
          "max": 47,
          "count": 117,
          "mean": 7.5,
          "p50": 6,
          "median": 6,
          "p75": 7,
          "p90": 8.9,
          "p95": 13.9,
          "p99": 16,
          "p999": 18
        },
        "http.response_time.2xx": {
          "min": 5,
          "max": 47,
          "count": 117,
          "mean": 7.5,
          "p50": 6,
          "median": 6,
          "p75": 7,
          "p90": 8.9,
          "p95": 13.9,
          "p99": 16,
          "p999": 18
        },
        "plugins.metrics-by-endpoint.response_time./api/v1/discussions": {
          "min": 5,
          "max": 47,
          "count": 117,
          "mean": 7.5,
          "p50": 6,
          "median": 6,
          "p75": 7,
          "p90": 8.9,
          "p95": 13.9,
          "p99": 16,
          "p999": 18
        },
        "vusers.session_length": {
          "min": 24,
          "max": 4123.8,
          "count": 44,
          "mean": 536.6,
          "p50": 89.1,
          "median": 89.1,
          "p75": 98.5,
          "p90": 135.7,
          "p95": 4065.2,
          "p99": 4147.4,
          "p999": 4147.4
        }
      }
    },
    {
      "counters": {
        "vusers.created_by_name.Create discussions with file attachments": 9,
        "vusers.created": 56,
        "requests.total": 17,
        "responses.201": 17,
        "requests.succeeded": 17,
        "vusers.created_by_name.Create discussions with text only": 47,
        "vusers.failed": 0,
        "vusers.completed": 54,
        "http.requests": 141,
        "http.codes.201": 141,
        "http.responses": 141,
        "http.downloaded_bytes": 119699,
        "plugins.metrics-by-endpoint./api/v1/discussions.codes.201": 141,
        "plugins.expect.ok": 141,
        "plugins.expect.ok.statusCode": 141
      },
      "rates": {
        "http.request_rate": 18
      },
      "http.request_rate": null,
      "firstCounterAt": 1743341450302,
      "firstHistogramAt": 1743341450457,
      "lastCounterAt": 1743341459788,
      "lastHistogramAt": 1743341459788,
      "firstMetricAt": 1743341450302,
      "lastMetricAt": 1743341459788,
      "period": "1743341450000",
      "summaries": {
        "vusers.session_length": {
          "min": 22.8,
          "max": 4132.6,
          "count": 54,
          "mean": 595,
          "p50": 89.1,
          "median": 89.1,
          "p75": 96.6,
          "p90": 4065.2,
          "p95": 4065.2,
          "p99": 4147.4,
          "p999": 4147.4
        },
        "http.response_time": {
          "min": 5,
          "max": 17,
          "count": 141,
          "mean": 7.5,
          "p50": 7,
          "median": 7,
          "p75": 7.9,
          "p90": 10.1,
          "p95": 12.1,
          "p99": 16.9,
          "p999": 16.9
        },
        "http.response_time.2xx": {
          "min": 5,
          "max": 17,
          "count": 141,
          "mean": 7.5,
          "p50": 7,
          "median": 7,
          "p75": 7.9,
          "p90": 10.1,
          "p95": 12.1,
          "p99": 16.9,
          "p999": 16.9
        },
        "plugins.metrics-by-endpoint.response_time./api/v1/discussions": {
          "min": 5,
          "max": 17,
          "count": 141,
          "mean": 7.5,
          "p50": 7,
          "median": 7,
          "p75": 7.9,
          "p90": 10.1,
          "p95": 12.1,
          "p99": 16.9,
          "p999": 16.9
        }
      },
      "histograms": {
        "vusers.session_length": {
          "min": 22.8,
          "max": 4132.6,
          "count": 54,
          "mean": 595,
          "p50": 89.1,
          "median": 89.1,
          "p75": 96.6,
          "p90": 4065.2,
          "p95": 4065.2,
          "p99": 4147.4,
          "p999": 4147.4
        },
        "http.response_time": {
          "min": 5,
          "max": 17,
          "count": 141,
          "mean": 7.5,
          "p50": 7,
          "median": 7,
          "p75": 7.9,
          "p90": 10.1,
          "p95": 12.1,
          "p99": 16.9,
          "p999": 16.9
        },
        "http.response_time.2xx": {
          "min": 5,
          "max": 17,
          "count": 141,
          "mean": 7.5,
          "p50": 7,
          "median": 7,
          "p75": 7.9,
          "p90": 10.1,
          "p95": 12.1,
          "p99": 16.9,
          "p999": 16.9
        },
        "plugins.metrics-by-endpoint.response_time./api/v1/discussions": {
          "min": 5,
          "max": 17,
          "count": 141,
          "mean": 7.5,
          "p50": 7,
          "median": 7,
          "p75": 7.9,
          "p90": 10.1,
          "p95": 12.1,
          "p99": 16.9,
          "p999": 16.9
        }
      }
    },
    {
      "counters": {
        "vusers.created_by_name.Create discussions with file attachments": 15,
        "vusers.created": 67,
        "vusers.failed": 0,
        "vusers.completed": 68,
        "requests.total": 31,
        "responses.201": 31,
        "requests.succeeded": 31,
        "vusers.created_by_name.Create discussions with text only": 52,
        "http.requests": 156,
        "http.codes.201": 156,
        "http.responses": 156,
        "http.downloaded_bytes": 131178,
        "plugins.metrics-by-endpoint./api/v1/discussions.codes.201": 156,
        "plugins.expect.ok": 156,
        "plugins.expect.ok.statusCode": 156
      },
      "rates": {
        "http.request_rate": 19
      },
      "http.request_rate": null,
      "firstCounterAt": 1743341460363,
      "firstHistogramAt": 1743341460416,
      "lastCounterAt": 1743341469916,
      "lastHistogramAt": 1743341469916,
      "firstMetricAt": 1743341460363,
      "lastMetricAt": 1743341469916,
      "period": "1743341460000",
      "summaries": {
        "vusers.session_length": {
          "min": 22.8,
          "max": 4131.1,
          "count": 68,
          "mean": 1008.6,
          "p50": 87.4,
          "median": 87.4,
          "p75": 102.5,
          "p90": 4065.2,
          "p95": 4147.4,
          "p99": 4147.4,
          "p999": 4147.4
        },
        "http.response_time": {
          "min": 5,
          "max": 18,
          "count": 156,
          "mean": 7.5,
          "p50": 7,
          "median": 7,
          "p75": 7.9,
          "p90": 10.1,
          "p95": 12.1,
          "p99": 16.9,
          "p999": 16.9
        },
        "http.response_time.2xx": {
          "min": 5,
          "max": 18,
          "count": 156,
          "mean": 7.5,
          "p50": 7,
          "median": 7,
          "p75": 7.9,
          "p90": 10.1,
          "p95": 12.1,
          "p99": 16.9,
          "p999": 16.9
        },
        "plugins.metrics-by-endpoint.response_time./api/v1/discussions": {
          "min": 5,
          "max": 18,
          "count": 156,
          "mean": 7.5,
          "p50": 7,
          "median": 7,
          "p75": 7.9,
          "p90": 10.1,
          "p95": 12.1,
          "p99": 16.9,
          "p999": 16.9
        }
      },
      "histograms": {
        "vusers.session_length": {
          "min": 22.8,
          "max": 4131.1,
          "count": 68,
          "mean": 1008.6,
          "p50": 87.4,
          "median": 87.4,
          "p75": 102.5,
          "p90": 4065.2,
          "p95": 4147.4,
          "p99": 4147.4,
          "p999": 4147.4
        },
        "http.response_time": {
          "min": 5,
          "max": 18,
          "count": 156,
          "mean": 7.5,
          "p50": 7,
          "median": 7,
          "p75": 7.9,
          "p90": 10.1,
          "p95": 12.1,
          "p99": 16.9,
          "p999": 16.9
        },
        "http.response_time.2xx": {
          "min": 5,
          "max": 18,
          "count": 156,
          "mean": 7.5,
          "p50": 7,
          "median": 7,
          "p75": 7.9,
          "p90": 10.1,
          "p95": 12.1,
          "p99": 16.9,
          "p999": 16.9
        },
        "plugins.metrics-by-endpoint.response_time./api/v1/discussions": {
          "min": 5,
          "max": 18,
          "count": 156,
          "mean": 7.5,
          "p50": 7,
          "median": 7,
          "p75": 7.9,
          "p90": 10.1,
          "p95": 12.1,
          "p99": 16.9,
          "p999": 16.9
        }
      }
    },
    {
      "counters": {
        "vusers.created_by_name.Create discussions with text only": 41,
        "vusers.created": 47,
        "http.requests": 123,
        "http.codes.201": 123,
        "http.responses": 123,
        "http.downloaded_bytes": 104408,
        "plugins.metrics-by-endpoint./api/v1/discussions.codes.201": 123,
        "plugins.expect.ok": 123,
        "plugins.expect.ok.statusCode": 123,
        "vusers.failed": 0,
        "vusers.completed": 51,
        "requests.total": 13,
        "responses.201": 13,
        "requests.succeeded": 13,
        "vusers.created_by_name.Create discussions with file attachments": 6
      },
      "rates": {
        "http.request_rate": 28
      },
      "http.request_rate": null,
      "firstCounterAt": 1743341470435,
      "firstHistogramAt": 1743341470454,
      "lastCounterAt": 1743341479776,
      "lastHistogramAt": 1743341479776,
      "firstMetricAt": 1743341470435,
      "lastMetricAt": 1743341479776,
      "period": "1743341470000",
      "summaries": {
        "http.response_time": {
          "min": 5,
          "max": 48,
          "count": 123,
          "mean": 8.1,
          "p50": 7,
          "median": 7,
          "p75": 7.9,
          "p90": 10.9,
          "p95": 15,
          "p99": 16.9,
          "p999": 18
        },
        "http.response_time.2xx": {
          "min": 5,
          "max": 48,
          "count": 123,
          "mean": 8.1,
          "p50": 7,
          "median": 7,
          "p75": 7.9,
          "p90": 10.9,
          "p95": 15,
          "p99": 16.9,
          "p999": 18
        },
        "plugins.metrics-by-endpoint.response_time./api/v1/discussions": {
          "min": 5,
          "max": 48,
          "count": 123,
          "mean": 8.1,
          "p50": 7,
          "median": 7,
          "p75": 7.9,
          "p90": 10.9,
          "p95": 15,
          "p99": 16.9,
          "p999": 18
        },
        "vusers.session_length": {
          "min": 23.6,
          "max": 4117.4,
          "count": 51,
          "mean": 856.5,
          "p50": 89.1,
          "median": 89.1,
          "p75": 102.5,
          "p90": 4065.2,
          "p95": 4065.2,
          "p99": 4147.4,
          "p999": 4147.4
        }
      },
      "histograms": {
        "http.response_time": {
          "min": 5,
          "max": 48,
          "count": 123,
          "mean": 8.1,
          "p50": 7,
          "median": 7,
          "p75": 7.9,
          "p90": 10.9,
          "p95": 15,
          "p99": 16.9,
          "p999": 18
        },
        "http.response_time.2xx": {
          "min": 5,
          "max": 48,
          "count": 123,
          "mean": 8.1,
          "p50": 7,
          "median": 7,
          "p75": 7.9,
          "p90": 10.9,
          "p95": 15,
          "p99": 16.9,
          "p999": 18
        },
        "plugins.metrics-by-endpoint.response_time./api/v1/discussions": {
          "min": 5,
          "max": 48,
          "count": 123,
          "mean": 8.1,
          "p50": 7,
          "median": 7,
          "p75": 7.9,
          "p90": 10.9,
          "p95": 15,
          "p99": 16.9,
          "p999": 18
        },
        "vusers.session_length": {
          "min": 23.6,
          "max": 4117.4,
          "count": 51,
          "mean": 856.5,
          "p50": 89.1,
          "median": 89.1,
          "p75": 102.5,
          "p90": 4065.2,
          "p95": 4065.2,
          "p99": 4147.4,
          "p999": 4147.4
        }
      }
    }
  ]
}