{
  "aggregate": {
    "counters": {
      "vusers.created_by_name.Create discussions with file attachments": 41,
      "vusers.created": 270,
      "requests.total": 82,
      "responses.201": 82,
      "requests.succeeded": 82,
      "vusers.created_by_name.Create discussions with text only": 229,
      "http.requests": 687,
      "http.codes.201": 687,
      "http.responses": 687,
      "http.downloaded_bytes": 579617,
      "plugins.metrics-by-endpoint./api/v1/discussions.codes.201": 687,
      "plugins.expect.ok": 687,
      "plugins.expect.ok.statusCode": 687,
      "vusers.failed": 0,
      "vusers.completed": 270
    },
    "rates": {
      "http.request_rate": 7
    },
    "firstCounterAt": 1743186010239,
    "firstHistogramAt": 1743186012335,
    "lastCounterAt": 1743186074235,
    "lastHistogramAt": 1743186074235,
    "firstMetricAt": 1743186010239,
    "lastMetricAt": 1743186074235,
    "period": 1743186070000,
    "summaries": {
      "http.response_time": {
        "min": 5,
        "max": 56,
        "count": 687,
        "mean": 8.5,
        "p50": 7.9,
        "median": 7.9,
        "p75": 8.9,
        "p90": 10.9,
        "p95": 16,
        "p99": 19.1,
        "p999": 53
      },
      "http.response_time.2xx": {
        "min": 5,
        "max": 56,
        "count": 687,
        "mean": 8.5,
        "p50": 7.9,
        "median": 7.9,
        "p75": 8.9,
        "p90": 10.9,
        "p95": 16,
        "p99": 19.1,
        "p999": 53
      },
      "plugins.metrics-by-endpoint.response_time./api/v1/discussions": {
        "min": 5,
        "max": 56,
        "count": 687,
        "mean": 8.5,
        "p50": 7.9,
        "median": 7.9,
        "p75": 8.9,
        "p90": 10.9,
        "p95": 16,
        "p99": 19.1,
        "p999": 53
      },
      "vusers.session_length": {
        "min": 24.2,
        "max": 4195.7,
        "count": 270,
        "mean": 687.1,
        "p50": 90.9,
        "median": 90.9,
        "p75": 102.5,
        "p90": 4065.2,
        "p95": 4147.4,
        "p99": 4147.4,
        "p999": 4147.4
      }
    },
    "histograms": {
      "http.response_time": {
        "min": 5,
        "max": 56,
        "count": 687,
        "mean": 8.5,
        "p50": 7.9,
        "median": 7.9,
        "p75": 8.9,
        "p90": 10.9,
        "p95": 16,
        "p99": 19.1,
        "p999": 53
      },
      "http.response_time.2xx": {
        "min": 5,
        "max": 56,
        "count": 687,
        "mean": 8.5,
        "p50": 7.9,
        "median": 7.9,
        "p75": 8.9,
        "p90": 10.9,
        "p95": 16,
        "p99": 19.1,
        "p999": 53
      },
      "plugins.metrics-by-endpoint.response_time./api/v1/discussions": {
        "min": 5,
        "max": 56,
        "count": 687,
        "mean": 8.5,
        "p50": 7.9,
        "median": 7.9,
        "p75": 8.9,
        "p90": 10.9,
        "p95": 16,
        "p99": 19.1,
        "p999": 53
      },
      "vusers.session_length": {
        "min": 24.2,
        "max": 4195.7,
        "count": 270,
        "mean": 687.1,
        "p50": 90.9,
        "median": 90.9,
        "p75": 102.5,
        "p90": 4065.2,
        "p95": 4147.4,
        "p99": 4147.4,
        "p999": 4147.4
      }
    }
  },
  "intermediate": [
    {
      "counters": {
        "vusers.created_by_name.Create discussions with file attachments": 3,
        "vusers.created": 15,
        "requests.total": 6,
        "responses.201": 6,
        "requests.succeeded": 6,
        "vusers.created_by_name.Create discussions with text only": 12,
        "http.requests": 36,
        "http.codes.201": 36,
        "http.responses": 36,
        "http.downloaded_bytes": 29794,
        "plugins.metrics-by-endpoint./api/v1/discussions.codes.201": 36,
        "plugins.expect.ok": 36,
        "plugins.expect.ok.statusCode": 36,
        "vusers.failed": 0,
        "vusers.completed": 14
      },
      "rates": {
        "http.request_rate": 7
      },
      "http.request_rate": null,
      "firstCounterAt": 1743186010239,
      "firstHistogramAt": 1743186012335,
      "lastCounterAt": 1743186019436,
      "lastHistogramAt": 1743186019436,
      "firstMetricAt": 1743186010239,
      "lastMetricAt": 1743186019436,
      "period": "1743186010000",
      "summaries": {
        "http.response_time": {
          "min": 7,
          "max": 53,
          "count": 36,
          "mean": 11.3,
          "p50": 8.9,
          "median": 8.9,
          "p75": 10.1,
          "p90": 16.9,
          "p95": 19.1,
          "p99": 21.1,
          "p999": 21.1
        },
        "http.response_time.2xx": {
          "min": 7,
          "max": 53,
          "count": 36,
          "mean": 11.3,
          "p50": 8.9,
          "median": 8.9,
          "p75": 10.1,
          "p90": 16.9,
          "p95": 19.1,
          "p99": 21.1,
          "p999": 21.1
        },
        "plugins.metrics-by-endpoint.response_time./api/v1/discussions": {
          "min": 7,
          "max": 53,
          "count": 36,
          "mean": 11.3,
          "p50": 8.9,
          "median": 8.9,
          "p75": 10.1,
          "p90": 16.9,
          "p95": 19.1,
          "p99": 21.1,
          "p999": 21.1
        },
        "vusers.session_length": {
          "min": 44.9,
          "max": 4195.7,
          "count": 14,
          "mean": 685.9,
          "p50": 106.7,
          "median": 106.7,
          "p75": 113.3,
          "p90": 172.5,
          "p95": 4147.4,
          "p99": 4147.4,
          "p999": 4147.4
        }
      },
      "histograms": {
        "http.response_time": {
          "min": 7,
          "max": 53,
          "count": 36,
          "mean": 11.3,
          "p50": 8.9,
          "median": 8.9,
          "p75": 10.1,
          "p90": 16.9,
          "p95": 19.1,
          "p99": 21.1,
          "p999": 21.1
        },
        "http.response_time.2xx": {
          "min": 7,
          "max": 53,
          "count": 36,
          "mean": 11.3,
          "p50": 8.9,
          "median": 8.9,
          "p75": 10.1,
          "p90": 16.9,
          "p95": 19.1,
          "p99": 21.1,
          "p999": 21.1
        },
        "plugins.metrics-by-endpoint.response_time./api/v1/discussions": {
          "min": 7,
          "max": 53,
          "count": 36,
          "mean": 11.3,
          "p50": 8.9,
          "median": 8.9,
          "p75": 10.1,
          "p90": 16.9,
          "p95": 19.1,
          "p99": 21.1,
          "p999": 21.1
        },
        "vusers.session_length": {
          "min": 44.9,
          "max": 4195.7,
          "count": 14,
          "mean": 685.9,
          "p50": 106.7,
          "median": 106.7,
          "p75": 113.3,
          "p90": 172.5,
          "p95": 4147.4,
          "p99": 4147.4,
          "p999": 4147.4
        }
      }
    },
    {
      "counters": {
        "vusers.created_by_name.Create discussions with text only": 23,
        "vusers.created": 27,
        "http.requests": 69,
        "http.codes.201": 69,
        "http.responses": 69,
        "http.downloaded_bytes": 57625,
        "plugins.metrics-by-endpoint./api/v1/discussions.codes.201": 69,
        "plugins.expect.ok": 69,
        "plugins.expect.ok.statusCode": 69,
        "vusers.failed": 0,
        "vusers.completed": 26,
        "vusers.created_by_name.Create discussions with file attachments": 4,
        "requests.total": 7,
        "responses.201": 7,
        "requests.succeeded": 7
      },
      "rates": {
        "http.request_rate": 10
      },
      "http.request_rate": null,
      "firstCounterAt": 1743186020286,
      "firstHistogramAt": 1743186020371,
      "lastCounterAt": 1743186029592,
      "lastHistogramAt": 1743186029592,
      "firstMetricAt": 1743186020286,
      "lastMetricAt": 1743186029592,
      "period": "1743186020000",
      "summaries": {
        "http.response_time": {
          "min": 6,
          "max": 27,
          "count": 69,
          "mean": 9.8,
          "p50": 7.9,
          "median": 7.9,
          "p75": 8.9,
          "p90": 16.9,
          "p95": 19.1,
          "p99": 25.8,
          "p999": 25.8
        },
        "http.response_time.2xx": {
          "min": 6,
          "max": 27,
          "count": 69,
          "mean": 9.8,
          "p50": 7.9,
          "median": 7.9,
          "p75": 8.9,
          "p90": 16.9,
          "p95": 19.1,
          "p99": 25.8,
          "p999": 25.8
        },
        "plugins.metrics-by-endpoint.response_time./api/v1/discussions": {
          "min": 6,
          "max": 27,
          "count": 69,
          "mean": 9.8,
          "p50": 7.9,
          "median": 7.9,
          "p75": 8.9,
          "p90": 16.9,
          "p95": 19.1,
          "p99": 25.8,
          "p999": 25.8
        },
        "vusers.session_length": {
          "min": 42.2,
          "max": 4133.6,
          "count": 26,
          "mean": 555.1,
          "p50": 92.8,
          "median": 92.8,
          "p75": 102.5,
          "p90": 117.9,
          "p95": 4147.4,
          "p99": 4147.4,
          "p999": 4147.4
        }
      },
      "histograms": {
        "http.response_time": {
          "min": 6,
          "max": 27,
          "count": 69,
          "mean": 9.8,
          "p50": 7.9,
          "median": 7.9,
          "p75": 8.9,
          "p90": 16.9,
          "p95": 19.1,
          "p99": 25.8,
          "p999": 25.8
        },
        "http.response_time.2xx": {
          "min": 6,
          "max": 27,
          "count": 69,
          "mean": 9.8,
          "p50": 7.9,
          "median": 7.9,
          "p75": 8.9,
          "p90": 16.9,
          "p95": 19.1,
          "p99": 25.8,
          "p999": 25.8
        },
        "plugins.metrics-by-endpoint.response_time./api/v1/discussions": {
          "min": 6,
          "max": 27,
          "count": 69,
          "mean": 9.8,
          "p50": 7.9,
          "median": 7.9,
          "p75": 8.9,
          "p90": 16.9,
          "p95": 19.1,
          "p99": 25.8,
          "p999": 25.8
        },
        "vusers.session_length": {
          "min": 42.2,
          "max": 4133.6,
          "count": 26,
          "mean": 555.1,
          "p50": 92.8,
          "median": 92.8,
          "p75": 102.5,
          "p90": 117.9,
          "p95": 4147.4,
          "p99": 4147.4,
          "p999": 4147.4
        }
      }
    },
    {
      "counters": {
        "vusers.created_by_name.Create discussions with text only": 32,
        "vusers.created": 38,
        "requests.total": 11,
        "responses.201": 11,
        "requests.succeeded": 11,
        "http.requests": 96,
        "http.codes.201": 96,
        "http.responses": 96,
        "http.downloaded_bytes": 81393,
        "plugins.metrics-by-endpoint./api/v1/discussions.codes.201": 96,
        "plugins.expect.ok": 96,
        "plugins.expect.ok.statusCode": 96,
        "vusers.failed": 0,
        "vusers.completed": 37,
        "vusers.created_by_name.Create discussions with file attachments": 6
      },
      "rates": {
        "http.request_rate": 11
      },
      "http.request_rate": null,
      "firstCounterAt": 1743186030315,
      "firstHistogramAt": 1743186030390,
      "lastCounterAt": 1743186039705,
      "lastHistogramAt": 1743186039705,
      "firstMetricAt": 1743186030315,
      "lastMetricAt": 1743186039705,
      "period": "1743186030000",
      "summaries": {
        "http.response_time": {
          "min": 6,
          "max": 18,
          "count": 96,
          "mean": 8.7,
          "p50": 7.9,
          "median": 7.9,
          "p75": 8.9,
          "p90": 10.9,
          "p95": 16,
          "p99": 18,
          "p999": 18
        },
        "http.response_time.2xx": {
          "min": 6,
          "max": 18,
          "count": 96,
          "mean": 8.7,
          "p50": 7.9,
          "median": 7.9,
          "p75": 8.9,
          "p90": 10.9,
          "p95": 16,
          "p99": 18,
          "p999": 18
        },
        "plugins.metrics-by-endpoint.response_time./api/v1/discussions": {
          "min": 6,
          "max": 18,
          "count": 96,
          "mean": 8.7,
          "p50": 7.9,
          "median": 7.9,
          "p75": 8.9,
          "p90": 10.9,
          "p95": 16,
          "p99": 18,
          "p999": 18
        },
        "vusers.session_length": {
          "min": 26.1,
          "max": 4110.7,
          "count": 37,
          "mean": 614.3,
          "p50": 92.8,
          "median": 92.8,
          "p75": 102.5,
          "p90": 4065.2,
          "p95": 4065.2,
          "p99": 4065.2,
          "p999": 4065.2
        }
      },
      "histograms": {
        "http.response_time": {
          "min": 6,
          "max": 18,
          "count": 96,
          "mean": 8.7,
          "p50": 7.9,
          "median": 7.9,
          "p75": 8.9,
          "p90": 10.9,
          "p95": 16,
          "p99": 18,
          "p999": 18
        },
        "http.response_time.2xx": {
          "min": 6,
          "max": 18,
          "count": 96,
          "mean": 8.7,
          "p50": 7.9,
          "median": 7.9,
          "p75": 8.9,
          "p90": 10.9,
          "p95": 16,
          "p99": 18,
          "p999": 18
        },
        "plugins.metrics-by-endpoint.response_time./api/v1/discussions": {
          "min": 6,
          "max": 18,
          "count": 96,
          "mean": 8.7,
          "p50": 7.9,
          "median": 7.9,
          "p75": 8.9,
          "p90": 10.9,
          "p95": 16,
          "p99": 18,
          "p999": 18
        },
        "vusers.session_length": {
          "min": 26.1,
          "max": 4110.7,
          "count": 37,
          "mean": 614.3,
          "p50": 92.8,
          "median": 92.8,
          "p75": 102.5,
          "p90": 4065.2,
          "p95": 4065.2,
          "p99": 4065.2,
          "p999": 4065.2
        }
      }
    },
    {
      "counters": {
        "vusers.created_by_name.Create discussions with file attachments": 8,
        "vusers.created": 52,
        "requests.total": 15,
        "responses.201": 15,
        "requests.succeeded": 15,
        "vusers.created_by_name.Create discussions with text only": 44,
        "http.requests": 132,
        "http.codes.201": 132,
        "http.responses": 132,
        "http.downloaded_bytes": 111095,
        "plugins.metrics-by-endpoint./api/v1/discussions.codes.201": 132,
        "plugins.expect.ok": 132,
        "plugins.expect.ok.statusCode": 132,
        "vusers.failed": 0,
        "vusers.completed": 52
      },
      "rates": {
        "http.request_rate": 18
      },
      "http.request_rate": null,
      "firstCounterAt": 1743186040382,
      "firstHistogramAt": 1743186040540,
      "lastCounterAt": 1743186049891,
      "lastHistogramAt": 1743186049891,
      "firstMetricAt": 1743186040382,
      "lastMetricAt": 1743186049891,
      "period": "1743186040000",
      "summaries": {
        "http.response_time": {
          "min": 6,
          "max": 19,
          "count": 132,
          "mean": 7.8,
          "p50": 7,
          "median": 7,
          "p75": 7.9,
          "p90": 8.9,
          "p95": 10.1,
          "p99": 16.9,
          "p999": 18
        },
        "http.response_time.2xx": {
          "min": 6,
          "max": 19,
          "count": 132,
          "mean": 7.8,
          "p50": 7,
          "median": 7,
          "p75": 7.9,
          "p90": 8.9,
          "p95": 10.1,
          "p99": 16.9,
          "p999": 18
        },
        "plugins.metrics-by-endpoint.response_time./api/v1/discussions": {
          "min": 6,
          "max": 19,
          "count": 132,
          "mean": 7.8,
          "p50": 7,
          "median": 7,
          "p75": 7.9,
          "p90": 8.9,
          "p95": 10.1,
          "p99": 16.9,
          "p999": 18
        },
        "vusers.session_length": {
          "min": 25.6,
          "max": 4150.9,
          "count": 52,
          "mean": 699.3,
          "p50": 90.9,
          "median": 90.9,
          "p75": 92.8,
          "p90": 4065.2,
          "p95": 4147.4,
          "p99": 4147.4,
          "p999": 4147.4
        }
      },
      "histograms": {
        "http.response_time": {
          "min": 6,
          "max": 19,
          "count": 132,
          "mean": 7.8,
          "p50": 7,
          "median": 7,
          "p75": 7.9,
          "p90": 8.9,
          "p95": 10.1,
          "p99": 16.9,
          "p999": 18
        },
        "http.response_time.2xx": {
          "min": 6,
          "max": 19,
          "count": 132,
          "mean": 7.8,
          "p50": 7,
          "median": 7,
          "p75": 7.9,
          "p90": 8.9,
          "p95": 10.1,
          "p99": 16.9,
          "p999": 18
        },
        "plugins.metrics-by-endpoint.response_time./api/v1/discussions": {
          "min": 6,
          "max": 19,
          "count": 132,
          "mean": 7.8,
          "p50": 7,
          "median": 7,
          "p75": 7.9,
          "p90": 8.9,
          "p95": 10.1,
          "p99": 16.9,
          "p999": 18
        },
        "vusers.session_length": {
          "min": 25.6,
          "max": 4150.9,
          "count": 52,
          "mean": 699.3,
          "p50": 90.9,
          "median": 90.9,
          "p75": 92.8,
          "p90": 4065.2,
          "p95": 4147.4,
          "p99": 4147.4,
          "p999": 4147.4
        }
      }
    },
    {
      "counters": {
        "vusers.created_by_name.Create discussions with text only": 55,
        "vusers.created": 63,
        "http.requests": 165,
        "http.codes.201": 165,
        "http.responses": 165,
        "http.downloaded_bytes": 139618,
        "plugins.metrics-by-endpoint./api/v1/discussions.codes.201": 165,
        "plugins.expect.ok": 165,
        "plugins.expect.ok.statusCode": 165,
        "vusers.failed": 0,
        "vusers.completed": 62,
        "requests.total": 16,
        "responses.201": 16,
        "requests.succeeded": 16,
        "vusers.created_by_name.Create discussions with file attachments": 8
      },
      "rates": {
        "http.request_rate": 20
      },
      "http.request_rate": null,
      "firstCounterAt": 1743186050437,
      "firstHistogramAt": 1743186050455,
      "lastCounterAt": 1743186059971,
      "lastHistogramAt": 1743186059971,
      "firstMetricAt": 1743186050437,
      "lastMetricAt": 1743186059971,
      "period": "1743186050000",
      "summaries": {
        "http.response_time": {
          "min": 6,
          "max": 56,
          "count": 165,
          "mean": 8.6,
          "p50": 7,
          "median": 7,
          "p75": 8.9,
          "p90": 10.9,
          "p95": 13.9,
          "p99": 18,
          "p999": 19.9
        },
        "http.response_time.2xx": {
          "min": 6,
          "max": 56,
          "count": 165,
          "mean": 8.6,
          "p50": 7,
          "median": 7,
          "p75": 8.9,
          "p90": 10.9,
          "p95": 13.9,
          "p99": 18,
          "p999": 19.9
        },
        "plugins.metrics-by-endpoint.response_time./api/v1/discussions": {
          "min": 6,
          "max": 56,
          "count": 165,
          "mean": 8.6,
          "p50": 7,
          "median": 7,
          "p75": 8.9,
          "p90": 10.9,
          "p95": 13.9,
          "p99": 18,
          "p999": 19.9
        },
        "vusers.session_length": {
          "min": 24.7,
          "max": 4165.5,
          "count": 62,
          "mean": 529,
          "p50": 90.9,
          "median": 90.9,
          "p75": 100.5,
          "p90": 147,
          "p95": 4147.4,
          "p99": 4147.4,
          "p999": 4147.4
        }
      },
      "histograms": {
        "http.response_time": {
          "min": 6,
          "max": 56,
          "count": 165,
          "mean": 8.6,
          "p50": 7,
          "median": 7,
          "p75": 8.9,
          "p90": 10.9,
          "p95": 13.9,
          "p99": 18,
          "p999": 19.9
        },
        "http.response_time.2xx": {
          "min": 6,
          "max": 56,
          "count": 165,
          "mean": 8.6,
          "p50": 7,
          "median": 7,
          "p75": 8.9,
          "p90": 10.9,
          "p95": 13.9,
          "p99": 18,
          "p999": 19.9
        },
        "plugins.metrics-by-endpoint.response_time./api/v1/discussions": {
          "min": 6,
          "max": 56,
          "count": 165,
          "mean": 8.6,
          "p50": 7,
          "median": 7,
          "p75": 8.9,
          "p90": 10.9,
          "p95": 13.9,
          "p99": 18,
          "p999": 19.9
        },
        "vusers.session_length": {
          "min": 24.7,
          "max": 4165.5,
          "count": 62,
          "mean": 529,
          "p50": 90.9,
          "median": 90.9,
          "p75": 100.5,
          "p90": 147,
          "p95": 4147.4,
          "p99": 4147.4,
          "p999": 4147.4
        }
      }
    },
    {
      "counters": {
        "vusers.created_by_name.Create discussions with text only": 63,
        "vusers.created": 74,
        "http.requests": 186,
        "http.codes.201": 186,
        "http.responses": 186,
        "http.downloaded_bytes": 157866,
        "plugins.metrics-by-endpoint./api/v1/discussions.codes.201": 186,
        "plugins.expect.ok": 186,
        "plugins.expect.ok.statusCode": 186,
        "vusers.failed": 0,
        "vusers.completed": 69,
        "requests.total": 22,
        "responses.201": 22,
        "requests.succeeded": 22,
        "vusers.created_by_name.Create discussions with file attachments": 11
      },
      "rates": {
        "http.request_rate": 27
      },
      "http.request_rate": null,
      "firstCounterAt": 1743186060530,
      "firstHistogramAt": 1743186060614,
      "lastCounterAt": 1743186069982,
      "lastHistogramAt": 1743186069982,
      "firstMetricAt": 1743186060530,
      "lastMetricAt": 1743186069982,
      "period": "1743186060000",
      "summaries": {
        "http.response_time": {
          "min": 5,
          "max": 18,
          "count": 186,
          "mean": 7.8,
          "p50": 7,
          "median": 7,
          "p75": 7.9,
          "p90": 8.9,
          "p95": 10.9,
          "p99": 16.9,
          "p999": 16.9
        },
        "http.response_time.2xx": {
          "min": 5,
          "max": 18,
          "count": 186,
          "mean": 7.8,
          "p50": 7,
          "median": 7,
          "p75": 7.9,
          "p90": 8.9,
          "p95": 10.9,
          "p99": 16.9,
          "p999": 16.9
        },
        "plugins.metrics-by-endpoint.response_time./api/v1/discussions": {
          "min": 5,
          "max": 18,
          "count": 186,
          "mean": 7.8,
          "p50": 7,
          "median": 7,
          "p75": 7.9,
          "p90": 8.9,
          "p95": 10.9,
          "p99": 16.9,
          "p999": 16.9
        },
        "vusers.session_length": {
          "min": 24.2,
          "max": 4116.8,
          "count": 69,
          "mean": 473.6,
          "p50": 87.4,
          "median": 87.4,
          "p75": 94.6,
          "p90": 108.9,
          "p95": 4065.2,
          "p99": 4147.4,
          "p999": 4147.4
        }
      },
      "histograms": {
        "http.response_time": {
          "min": 5,
          "max": 18,
          "count": 186,
          "mean": 7.8,
          "p50": 7,
          "median": 7,
          "p75": 7.9,
          "p90": 8.9,
          "p95": 10.9,
          "p99": 16.9,
          "p999": 16.9
        },
        "http.response_time.2xx": {
          "min": 5,
          "max": 18,
          "count": 186,
          "mean": 7.8,
          "p50": 7,
          "median": 7,
          "p75": 7.9,
          "p90": 8.9,
          "p95": 10.9,
          "p99": 16.9,
          "p999": 16.9
        },
        "plugins.metrics-by-endpoint.response_time./api/v1/discussions": {
          "min": 5,
          "max": 18,
          "count": 186,
          "mean": 7.8,
          "p50": 7,
          "median": 7,
          "p75": 7.9,
          "p90": 8.9,
          "p95": 10.9,
          "p99": 16.9,
          "p999": 16.9
        },
        "vusers.session_length": {
          "min": 24.2,
          "max": 4116.8,
          "count": 69,
          "mean": 473.6,
          "p50": 87.4,
          "median": 87.4,
          "p75": 94.6,
          "p90": 108.9,
          "p95": 4065.2,
          "p99": 4147.4,
          "p999": 4147.4
        }
      }
    },
    {
      "counters": {
        "vusers.failed": 0,
        "vusers.completed": 10,
        "http.requests": 3,
        "http.codes.201": 3,
        "http.responses": 3,
        "http.downloaded_bytes": 2226,
        "plugins.metrics-by-endpoint./api/v1/discussions.codes.201": 3,
        "plugins.expect.ok": 3,
        "plugins.expect.ok.statusCode": 3,
        "requests.total": 5,
        "responses.201": 5,
        "requests.succeeded": 5,
        "vusers.created_by_name.Create discussions with file attachments": 1,
        "vusers.created": 1
      },
      "rates": {
        "http.request_rate": 3
      },
      "firstCounterAt": 1743186070000,
      "firstHistogramAt": 1743186070007,
      "lastCounterAt": 1743186074235,
      "lastHistogramAt": 1743186074235,
      "firstMetricAt": 1743186070000,
      "lastMetricAt": 1743186074235,
      "period": "1743186070000",
      "http.request_rate": null,
      "summaries": {
        "vusers.session_length": {
          "min": 86,
          "max": 4143.5,
          "count": 10,
          "mean": 3690.8,
          "p50": 4065.2,
          "median": 4065.2,
          "p75": 4147.4,
          "p90": 4147.4,
          "p95": 4147.4,
          "p99": 4147.4,
          "p999": 4147.4
        },
        "http.response_time": {
          "min": 5,
          "max": 6,
          "count": 3,
          "mean": 5.7,
          "p50": 6,
          "median": 6,
          "p75": 6,
          "p90": 6,
          "p95": 6,
          "p99": 6,
          "p999": 6
        },
        "http.response_time.2xx": {
          "min": 5,
          "max": 6,
          "count": 3,
          "mean": 5.7,
          "p50": 6,
          "median": 6,
          "p75": 6,
          "p90": 6,
          "p95": 6,
          "p99": 6,
          "p999": 6
        },
        "plugins.metrics-by-endpoint.response_time./api/v1/discussions": {
          "min": 5,
          "max": 6,
          "count": 3,
          "mean": 5.7,
          "p50": 6,
          "median": 6,
          "p75": 6,
          "p90": 6,
          "p95": 6,
          "p99": 6,
          "p999": 6
        }
      },
      "histograms": {
        "vusers.session_length": {
          "min": 86,
          "max": 4143.5,
          "count": 10,
          "mean": 3690.8,
          "p50": 4065.2,
          "median": 4065.2,
          "p75": 4147.4,
          "p90": 4147.4,
          "p95": 4147.4,
          "p99": 4147.4,
          "p999": 4147.4
        },
        "http.response_time": {
          "min": 5,
          "max": 6,
          "count": 3,
          "mean": 5.7,
          "p50": 6,
          "median": 6,
          "p75": 6,
          "p90": 6,
          "p95": 6,
          "p99": 6,
          "p999": 6
        },
        "http.response_time.2xx": {
          "min": 5,
          "max": 6,
          "count": 3,
          "mean": 5.7,
          "p50": 6,
          "median": 6,
          "p75": 6,
          "p90": 6,
          "p95": 6,
          "p99": 6,
          "p999": 6
        },
        "plugins.metrics-by-endpoint.response_time./api/v1/discussions": {
          "min": 5,
          "max": 6,
          "count": 3,
          "mean": 5.7,
          "p50": 6,
          "median": 6,
          "p75": 6,
          "p90": 6,
          "p95": 6,
          "p99": 6,
          "p999": 6
        }
      }
    }
  ]
}